HurricaneDNS.py
hurricanedns-1.0.2.data/scripts/hurricanedns
hurricanedns-1.0.2.dist-info/DESCRIPTION.rst
hurricanedns-1.0.2.dist-info/METADATA
hurricanedns-1.0.2.dist-info/RECORD
hurricanedns-1.0.2.dist-info/WHEEL
hurricanedns-1.0.2.dist-info/metadata.json
hurricanedns-1.0.2.dist-info/top_level.txt
