Metadata-Version: 2.0
Name: hurricanedns
Version: 1.0.2
Summary: Hurricane Electric DNS python library
Home-page: https://github.com/tresni/pyhurricanedns
Author: Brian Hartvigsen
Author-email: brian.andrew@brianandjenny.com
License: UNKNOWN
Platform: UNKNOWN
Classifier: Development Status :: 5 - Production/Stable
Classifier: Environment :: Console
Classifier: Intended Audience :: Information Technology
Classifier: Intended Audience :: System Administrators
Classifier: License :: OSI Approved :: MIT License
Classifier: Operating System :: OS Independent
Classifier: Programming Language :: Python
Classifier: Programming Language :: Python :: 2
Classifier: Programming Language :: Python :: 2.7
Classifier: Programming Language :: Python :: 3
Classifier: Programming Language :: Python :: 3.5
Classifier: Topic :: Internet :: Name Service (DNS)
Classifier: Topic :: Utilities
Requires-Dist: html5lib
Requires-Dist: lxml
Provides-Extra: import
Requires-Dist: dnspython; extra == 'import'
